<?xml version="1.0" encoding="UTF-8"?>
<TextureAtlas imagePath="commision_Sprite2.png">
	<!-- Created with Adobe Flash CS6 version 12.0.0.481 -->
	<!-- http://www.adobe.com/products/flash.html -->
	<SubTexture name="Down0000" x="0" y="0" width="914" height="913"/>
	<SubTexture name="Down0001" x="0" y="0" width="914" height="913"/>
	<SubTexture name="Down0002" x="914" y="0" width="914" height="913"/>
	<SubTexture name="Down0003" x="1828" y="0" width="914" height="913"/>
	<SubTexture name="Down0004" x="2742" y="0" width="914" height="913"/>
	<SubTexture name="Down0005" x="3656" y="0" width="914" height="913"/>
	<SubTexture name="Down0006" x="3656" y="0" width="914" height="913"/>
	<SubTexture name="Down0007" x="4570" y="0" width="914" height="913"/>
	<SubTexture name="Down0008" x="4570" y="0" width="914" height="913"/>
	<SubTexture name="Down0009" x="3656" y="0" width="914" height="913"/>
	<SubTexture name="Idle0000" x="5484" y="0" width="769" height="908"/>
	<SubTexture name="Idle0001" x="5484" y="0" width="769" height="908"/>
	<SubTexture name="Idle0002" x="6253" y="0" width="769" height="908"/>
	<SubTexture name="Idle0003" x="6253" y="0" width="769" height="908"/>
	<SubTexture name="Idle0004" x="7022" y="0" width="769" height="908"/>
	<SubTexture name="Idle0005" x="7022" y="0" width="769" height="908"/>
	<SubTexture name="Idle0006" x="0" y="913" width="769" height="908"/>
	<SubTexture name="Idle0007" x="0" y="913" width="769" height="908"/>
	<SubTexture name="Idle0008" x="769" y="913" width="769" height="908"/>
	<SubTexture name="Idle0009" x="769" y="913" width="769" height="908"/>
	<SubTexture name="Idle0010" x="0" y="913" width="769" height="908"/>
	<SubTexture name="Idle0011" x="0" y="913" width="769" height="908"/>
	<SubTexture name="Idle0012" x="769" y="913" width="769" height="908"/>
	<SubTexture name="Idle0013" x="769" y="913" width="769" height="908"/>
	<SubTexture name="Left0000" x="1538" y="913" width="912" height="752"/>
	<SubTexture name="Left0001" x="1538" y="913" width="912" height="752"/>
	<SubTexture name="Left0002" x="2450" y="913" width="912" height="752"/>
	<SubTexture name="Left0003" x="3362" y="913" width="912" height="752"/>
	<SubTexture name="Left0004" x="4274" y="913" width="912" height="752"/>
	<SubTexture name="Left0005" x="4274" y="913" width="912" height="752"/>
	<SubTexture name="Left0006" x="3362" y="913" width="912" height="752"/>
	<SubTexture name="Left0007" x="3362" y="913" width="912" height="752"/>
	<SubTexture name="Left0008" x="4274" y="913" width="912" height="752"/>
	<SubTexture name="Left0009" x="4274" y="913" width="912" height="752"/>
	<SubTexture name="Not_Bad0000" x="5186" y="913" width="764" height="908"/>
	<SubTexture name="Not_Bad0001" x="5186" y="913" width="764" height="908"/>
	<SubTexture name="Not_Bad0002" x="5950" y="913" width="764" height="908"/>
	<SubTexture name="Not_Bad0003" x="5950" y="913" width="764" height="908"/>
	<SubTexture name="Not_Bad0004" x="5186" y="913" width="764" height="908"/>
	<SubTexture name="Not_Bad0005" x="5186" y="913" width="764" height="908"/>
	<SubTexture name="Not_Bad0006" x="5950" y="913" width="764" height="908"/>
	<SubTexture name="Not_Bad0007" x="5950" y="913" width="764" height="908"/>
	<SubTexture name="Not_Bad0008" x="5186" y="913" width="764" height="908"/>
	<SubTexture name="Not_Bad0009" x="5186" y="913" width="764" height="908"/>
	<SubTexture name="Not_Bad0010" x="5950" y="913" width="764" height="908"/>
	<SubTexture name="Not_Bad0011" x="5950" y="913" width="764" height="908"/>
	<SubTexture name="Not_Bad0012" x="5186" y="913" width="764" height="908"/>
	<SubTexture name="Not_Bad0013" x="6714" y="913" width="764" height="908"/>
	<SubTexture name="Not_Bad0014" x="0" y="1821" width="764" height="908"/>
	<SubTexture name="Not_Bad0015" x="764" y="1821" width="764" height="908"/>
	<SubTexture name="Not_Bad0016" x="1528" y="1821" width="764" height="908"/>
	<SubTexture name="Not_Bad0017" x="1528" y="1821" width="764" height="908"/>
	<SubTexture name="Not_Bad0018" x="2292" y="1821" width="764" height="908"/>
	<SubTexture name="Not_Bad0019" x="2292" y="1821" width="764" height="908"/>
	<SubTexture name="Not_Bad0020" x="3056" y="1821" width="764" height="908"/>
	<SubTexture name="Not_Bad0021" x="3056" y="1821" width="764" height="908"/>
	<SubTexture name="Not_Bad0022" x="3820" y="1821" width="764" height="908"/>
	<SubTexture name="Not_Bad0023" x="3820" y="1821" width="764" height="908"/>
	<SubTexture name="Not_Bad0024" x="4584" y="1821" width="764" height="908"/>
	<SubTexture name="Not_Bad0025" x="4584" y="1821" width="764" height="908"/>
	<SubTexture name="Not_Bad0026" x="3820" y="1821" width="764" height="908"/>
	<SubTexture name="Not_Bad0027" x="3820" y="1821" width="764" height="908"/>
	<SubTexture name="Not_Bad0028" x="4584" y="1821" width="764" height="908"/>
	<SubTexture name="Not_Bad0029" x="4584" y="1821" width="764" height="908"/>
	<SubTexture name="Not_Bad0030" x="3820" y="1821" width="764" height="908"/>
	<SubTexture name="Not_Bad0031" x="3820" y="1821" width="764" height="908"/>
	<SubTexture name="Not_Bad0032" x="4584" y="1821" width="764" height="908"/>
	<SubTexture name="Not_Bad0033" x="4584" y="1821" width="764" height="908"/>
	<SubTexture name="Not_Bad0034" x="3820" y="1821" width="764" height="908"/>
	<SubTexture name="Not_Bad0035" x="3820" y="1821" width="764" height="908"/>
	<SubTexture name="Not_Bad0036" x="4584" y="1821" width="764" height="908"/>
	<SubTexture name="Not_Bad0037" x="4584" y="1821" width="764" height="908"/>
	<SubTexture name="Not_Bad0038" x="3820" y="1821" width="764" height="908"/>
	<SubTexture name="Not_Bad0039" x="3820" y="1821" width="764" height="908"/>
	<SubTexture name="Not_Bad0040" x="4584" y="1821" width="764" height="908"/>
	<SubTexture name="Not_Bad0041" x="4584" y="1821" width="764" height="908"/>
	<SubTexture name="Not_Bad0042" x="3820" y="1821" width="764" height="908"/>
	<SubTexture name="Not_Bad0043" x="3820" y="1821" width="764" height="908"/>
	<SubTexture name="Not_Bad0044" x="4584" y="1821" width="764" height="908"/>
	<SubTexture name="Not_Bad0045" x="4584" y="1821" width="764" height="908"/>
	<SubTexture name="Not_Bad0046" x="3820" y="1821" width="764" height="908"/>
	<SubTexture name="Not_Bad0047" x="3820" y="1821" width="764" height="908"/>
	<SubTexture name="Not_Bad0048" x="4584" y="1821" width="764" height="908"/>
	<SubTexture name="Not_Bad0049" x="4584" y="1821" width="764" height="908"/>
	<SubTexture name="Not_Bad0050" x="3820" y="1821" width="764" height="908"/>
	<SubTexture name="Not_Bad0051" x="3820" y="1821" width="764" height="908"/>
	<SubTexture name="Not_Bad0052" x="4584" y="1821" width="764" height="908"/>
	<SubTexture name="Not_Bad0053" x="4584" y="1821" width="764" height="908"/>
	<SubTexture name="Not_Bad0054" x="3820" y="1821" width="764" height="908"/>
	<SubTexture name="Not_Bad0055" x="3820" y="1821" width="764" height="908"/>
	<SubTexture name="Not_Bad0056" x="4584" y="1821" width="764" height="908"/>
	<SubTexture name="Not_Bad0057" x="4584" y="1821" width="764" height="908"/>
	<SubTexture name="Not_Bad0058" x="3820" y="1821" width="764" height="908"/>
	<SubTexture name="Not_Bad0059" x="3820" y="1821" width="764" height="908"/>
	<SubTexture name="Not_Bad0060" x="4584" y="1821" width="764" height="908"/>
	<SubTexture name="Not_Bad0061" x="4584" y="1821" width="764" height="908"/>
	<SubTexture name="Not_Bad0062" x="3820" y="1821" width="764" height="908"/>
	<SubTexture name="Not_Bad0063" x="3820" y="1821" width="764" height="908"/>
	<SubTexture name="Not_Bad0064" x="4584" y="1821" width="764" height="908"/>
	<SubTexture name="Not_Bad0065" x="4584" y="1821" width="764" height="908"/>
	<SubTexture name="Not_Bad0066" x="3820" y="1821" width="764" height="908"/>
	<SubTexture name="Not_Bad0067" x="3820" y="1821" width="764" height="908"/>
	<SubTexture name="Not_Bad0068" x="4584" y="1821" width="764" height="908"/>
	<SubTexture name="Not_Bad0069" x="4584" y="1821" width="764" height="908"/>
	<SubTexture name="Not_Bad0070" x="3820" y="1821" width="764" height="908"/>
	<SubTexture name="Not_Bad0071" x="3820" y="1821" width="764" height="908"/>
	<SubTexture name="Not_Bad0072" x="4584" y="1821" width="764" height="908"/>
	<SubTexture name="Not_Bad0073" x="4584" y="1821" width="764" height="908"/>
	<SubTexture name="Not_Bad0074" x="3820" y="1821" width="764" height="908"/>
	<SubTexture name="Not_Bad0075" x="3820" y="1821" width="764" height="908"/>
	<SubTexture name="Not_Bad0076" x="4584" y="1821" width="764" height="908"/>
	<SubTexture name="Not_Bad0077" x="4584" y="1821" width="764" height="908"/>
	<SubTexture name="Not_Bad0078" x="3820" y="1821" width="764" height="908"/>
	<SubTexture name="Not_Bad0079" x="3820" y="1821" width="764" height="908"/>
	<SubTexture name="Not_Bad0080" x="4584" y="1821" width="764" height="908"/>
	<SubTexture name="Not_Bad0081" x="4584" y="1821" width="764" height="908"/>
	<SubTexture name="Not_Bad0082" x="3820" y="1821" width="764" height="908"/>
	<SubTexture name="Not_Bad0083" x="3820" y="1821" width="764" height="908"/>
	<SubTexture name="Not_Bad0084" x="4584" y="1821" width="764" height="908"/>
	<SubTexture name="Not_Bad0085" x="4584" y="1821" width="764" height="908"/>
	<SubTexture name="Not_Bad0086" x="3820" y="1821" width="764" height="908"/>
	<SubTexture name="Not_Bad0087" x="3820" y="1821" width="764" height="908"/>
	<SubTexture name="Not_Bad0088" x="4584" y="1821" width="764" height="908"/>
	<SubTexture name="Not_Bad0089" x="4584" y="1821" width="764" height="908"/>
	<SubTexture name="Right0000" x="5348" y="1821" width="912" height="769"/>
	<SubTexture name="Right0001" x="5348" y="1821" width="912" height="769"/>
	<SubTexture name="Right0002" x="6260" y="1821" width="912" height="769"/>
	<SubTexture name="Right0003" x="7172" y="1821" width="912" height="769"/>
	<SubTexture name="Right0004" x="0" y="2729" width="912" height="769"/>
	<SubTexture name="Right0005" x="0" y="2729" width="912" height="769"/>
	<SubTexture name="Right0006" x="7172" y="1821" width="912" height="769"/>
	<SubTexture name="Right0007" x="7172" y="1821" width="912" height="769"/>
	<SubTexture name="Right0008" x="0" y="2729" width="912" height="769"/>
	<SubTexture name="Right0009" x="0" y="2729" width="912" height="769"/>
	<SubTexture name="Up0000" x="912" y="2729" width="735" height="932"/>
	<SubTexture name="Up0001" x="912" y="2729" width="735" height="932"/>
	<SubTexture name="Up0002" x="1647" y="2729" width="735" height="932"/>
	<SubTexture name="Up0003" x="2382" y="2729" width="735" height="932"/>
	<SubTexture name="Up0004" x="3117" y="2729" width="735" height="932"/>
	<SubTexture name="Up0005" x="3852" y="2729" width="735" height="932"/>
	<SubTexture name="Up0006" x="4587" y="2729" width="735" height="932"/>
	<SubTexture name="Up0007" x="4587" y="2729" width="735" height="932"/>
	<SubTexture name="Up0008" x="5322" y="2729" width="735" height="932"/>
	<SubTexture name="Up0009" x="5322" y="2729" width="735" height="932"/>
	<SubTexture name="Up0010" x="4587" y="2729" width="735" height="932"/>
	<SubTexture name="Up0011" x="4587" y="2729" width="735" height="932"/>
	<SubTexture name="Up0012" x="5322" y="2729" width="735" height="932"/>
	<SubTexture name="Up0013" x="5322" y="2729" width="735" height="932"/>
	<SubTexture name="Up0014" x="4587" y="2729" width="735" height="932"/>
	<SubTexture name="Up0015" x="4587" y="2729" width="735" height="932"/>
	<SubTexture name="Up0016" x="5322" y="2729" width="735" height="932"/>
	<SubTexture name="Up0017" x="5322" y="2729" width="735" height="932"/>
	<SubTexture name="Up0018" x="4587" y="2729" width="735" height="932"/>
	<SubTexture name="Up0019" x="4587" y="2729" width="735" height="932"/>
</TextureAtlas>
